taichi_meta/__init__.py
taichi_meta-0.1.1.dist-info/licenses/LICENSE
taichi_meta-0.1.1.dist-info/METADATA
taichi_meta-0.1.1.dist-info/WHEEL
taichi_meta-0.1.1.dist-info/top_level.txt
taichi_meta-0.1.1.dist-info/RECORD
