Metadata-Version: 2.4
Name: taichi-meta
Version: 0.1.1
Summary: A Simple Taichi Addon that allows you to compile AND recompile kernels directly from strings.
Home-page: https://github.com/pythagorasDesaster/taichi-meta
Author: Thomas Kirchner
Author-email: thomas.kirchner5@web.de
License: MIT License
Classifier: Development Status :: 1 - Planning
Classifier: Intended Audience :: Science/Research
Classifier: License :: OSI Approved :: MIT License
Classifier: Operating System :: POSIX :: Linux
Classifier: Programming Language :: Python :: 3
License-File: LICENSE
Requires-Dist: taichi>=1.0.0
Dynamic: author
Dynamic: author-email
Dynamic: classifier
Dynamic: description
Dynamic: description-content-type
Dynamic: home-page
Dynamic: license
Dynamic: license-file
Dynamic: requires-dist
Dynamic: summary
